falcon_dbapi/__init__.py
falcon_dbapi/exceptions.py
falcon_dbapi/middlewares/__init__.py
falcon_dbapi/middlewares/auth_middleware.py
falcon_dbapi/middlewares/html_middleware.py
falcon_dbapi/middlewares/json_middleware.py
falcon_dbapi/resources/__init__.py
falcon_dbapi/resources/base.py
falcon_dbapi/resources/elasticsearch.py
falcon_dbapi/resources/index.py
falcon_dbapi/resources/mongoengine.py
falcon_dbapi/resources/sqlalchemy.py
falcon_dbapi/resources/tests/__init__.py
falcon_dbapi/resources/tests/test_base.py
falcon_dbapi/resources/tests/test_create.py
falcon_dbapi/resources/tests/test_elasticsearch.py
falcon_dbapi/resources/tests/test_list.py
falcon_dbapi/resources/tests/test_sqlalchemy.py
falcon_dbapi/resources/tests/test_update.py
falcon_dbapi-1.2.4.dist-info/DESCRIPTION.rst
falcon_dbapi-1.2.4.dist-info/METADATA
falcon_dbapi-1.2.4.dist-info/RECORD
falcon_dbapi-1.2.4.dist-info/WHEEL
falcon_dbapi-1.2.4.dist-info/metadata.json
falcon_dbapi-1.2.4.dist-info/top_level.txt
