Metadata-Version: 2.0
Name: falcon-dbapi
Version: 1.2.4
Summary: Falcon API resources for databases
Home-page: https://github.com/opentopic/falcon-api
Author: Jan Waś
Author-email: jan.was@opentopic.com
License: MIT
Platform: OS Independent
Classifier: Development Status :: 4 - Beta
Classifier: Environment :: Web Environment
Classifier: Intended Audience :: Developers
Classifier: License :: OSI Approved :: MIT License
Classifier: Operating System :: OS Independent
Classifier: Programming Language :: Python :: 3.4
Classifier: Programming Language :: Python :: 3.5
Classifier: Programming Language :: Python :: 3.6
Requires-Dist: falcon (>=1.3.0)
